LICENSE.txt
MANIFEST.in
README.md
gg.py
requirements.txt
setup.py
QUsaco.egg-info/PKG-INFO
QUsaco.egg-info/SOURCES.txt
QUsaco.egg-info/dependency_links.txt
QUsaco.egg-info/entry_points.txt
QUsaco.egg-info/not-zip-safe
QUsaco.egg-info/requires.txt
QUsaco.egg-info/top_level.txt
qusaco/__init__.py
qusaco/qusaco.py