Metadata-Version: 2.1
Name: QUsaco
Version: 1.1
Summary: Judge USACO problems with stdin/stdout
Home-page: https://ryanchou.dev
Author: Ryan Chou
Author-email: 
License: MIT
Keywords: competitive-programming python java usaco cpp c++ problems testing
Platform: UNKNOWN
Classifier: Programming Language :: Python :: 3
Classifier: License :: OSI Approved :: MIT License
Classifier: Operating System :: OS Independent
